ECMpy/00.Model_preview.ipynb
ECMpy/01.get_reactiion_kcat_using_DLKcat.ipynb
ECMpy/01.get_reaction_kcat_using_AutoPACMEN.ipynb
ECMpy/02.get_ecModel_using_ECMpy.ipynb
ECMpy/03.ecModel_calibration.ipynb
ECMpy/04.ecModel_analysis.ipynb
ECMpy/05.ecModel_ME.ipynb
ECMpy/06.One-click_modeling.ipynb
ECMpy/AutoPACMEN_function.py
ECMpy/ECMpy_function.py
ECMpy/README.md
ECMpy/__init__.py
ECMpy/get_ecGEM_onestop.py
ECMpy/model.py
ECMpy/prediction_for_input.py
ECMpy/_cache/ncbi_taxonomy/Acanthamoeba castellanii_taxonomy
ECMpy/_cache/ncbi_taxonomy/Acetivibrio clariflavus_taxonomy
ECMpy/_cache/ncbi_taxonomy/Acetivibrio thermocellus_taxonomy
ECMpy/_cache/ncbi_taxonomy/Acetobacter aceti_taxonomy
ECMpy/_cache/ncbi_taxonomy/Acetobacter xylinus_taxonomy_NA
ECMpy/_cache/ncbi_taxonomy/Acetobacter_taxonomy
ECMpy/_cache/ncbi_taxonomy/Acetomicrobium mobile_taxonomy
ECMpy/_cache/ncbi_taxonomy/Acholeplasma laidlawii_taxonomy
ECMpy/_cache/ncbi_taxonomy/Acidilobus saccharovorans_taxonomy
ECMpy/_cache/ncbi_taxonomy/Acidithiobacillus ferrooxidans_taxonomy
ECMpy/_cache/ncbi_taxonomy/Acidithiobacillus thiooxidans_taxonomy
ECMpy/_cache/ncbi_taxonomy/Acinetobacter baumannii_taxonomy
ECMpy/_cache/ncbi_taxonomy/Acinetobacter baylyi_taxonomy
ECMpy/_cache/ncbi_taxonomy/Acinetobacter calcoaceticus (subsp. anitratus)_taxonomy_NA
ECMpy/_cache/ncbi_taxonomy/Acinetobacter calcoaceticus subsp. anitratus_taxonomy
ECMpy/_cache/ncbi_taxonomy/Acinetobacter calcoaceticus_taxonomy
ECMpy/_cache/ncbi_taxonomy/Acinetobacter sp._taxonomy
ECMpy/_cache/ncbi_taxonomy/Actinidia chinensis_taxonomy
ECMpy/_cache/ncbi_taxonomy/Actinomadura sp. R39_taxonomy
ECMpy/_cache/ncbi_taxonomy/Actinomadura sp._taxonomy
ECMpy/_cache/ncbi_taxonomy/Actinoplanes missouriensis_taxonomy
ECMpy/_cache/ncbi_taxonomy/Actinosynnema pretiosum subsp. auranticum_taxonomy
ECMpy/_cache/ncbi_taxonomy/Advenella mimigardefordensis_taxonomy
ECMpy/_cache/ncbi_taxonomy/Aedes aegypti_taxonomy
ECMpy/_cache/ncbi_taxonomy/Aeribacillus pallidus_taxonomy
ECMpy2.0-1.0.5.dist-info/METADATA
ECMpy2.0-1.0.5.dist-info/WHEEL
ECMpy2.0-1.0.5.dist-info/top_level.txt
ECMpy2.0-1.0.5.dist-info/RECORD
